dndclib.cpython-37m-darwin.so
dndclib-0.18.dist-info/METADATA
dndclib-0.18.dist-info/WHEEL
dndclib-0.18.dist-info/top_level.txt
dndclib-0.18.dist-info/RECORD
