Metadata-Version: 2.1
Name: dndclib
Version: 0.18
Summary: C++ Library of DNDC package
Home-page: http://www.dewscloud.com
Author: Feng
Author-email: dewscloud@gmail.com
License: GPL
Keywords: DNDC Core Libarary
Platform: UNKNOWN
Classifier: Development Status :: 1 - Planning
Classifier: Programming Language :: C++
Classifier: Topic :: Software Development
